[{"code": "070101001", "name": "池底板", "features": ["1.池形状、池深", "2.垫层材料种类、 厚度", "3.混凝土种类", "4.混凝土强度等级"], "unit": "m³"}, {"code": "070101002", "name": "池壁", "features": ["1.池形状、池深", "2.混凝土种类", "3.混凝土强度等级 4.壁厚"], "unit": "m³"}, {"code": "070101003", "name": "池顶板", "features": ["1.池形状", "2.板类型", "3.混凝土种类", "4.混凝土强度等级"], "unit": "m³"}, {"code": "070101004", "name": "池内柱", "features": ["1.混凝土种类", "2.混凝土强度等级", "3.柱形状及截面尺寸"], "unit": "m³"}, {"code": "070101005", "name": "池隔墙", "features": ["1.隔墙材料品种、规格", "2.材料强度等级", "3.墙体厚度"], "unit": "m³"}, {"code": "070102001", "name": "仓基础", "features": ["1.基础类型、埋深", "2.混凝土种类", "3.混凝土强度等级"], "unit": "m³"}, {"code": "070102002", "name": "仓底板", "features": ["1.仓类型", "2.仓截面尺寸", "3.仓底板厚度", "4.混凝土种类", "5.混凝土强度等级"], "unit": "m³"}, {"code": "070102003", "name": "仓壁", "features": ["1.仓类型", "2.仓截面尺寸及壁 厚", "3.仓壁高度", "4.混凝土种类", "5.混凝土强度等级"], "unit": "m³"}, {"code": "070102004", "name": "仓顶板", "features": ["1.仓类型", "2.仓截面尺寸", "3.顶板类型", "4.混凝土种类", "5.混凝土强度等级"], "unit": "m³"}, {"code": "070102005", "name": "仓内柱", "features": ["1.柱形状", "2.柱截面尺寸", "3.混凝土种类", "4.混凝土强度等级"], "unit": "m³"}, {"code": "070102006", "name": "仓内墙", "features": ["1.混凝土种类", "2.混凝土强度等级"], "unit": "m³"}, {"code": "070102007", "name": "仓底填料", "features": ["1.填料名称", "2.填料类别、强度等 级"], "unit": "m³"}, {"code": "070102008", "name": "仓漏斗", "features": ["1.漏斗形状", "2.混凝土种类", "3.混凝土强度等级"], "unit": "m³"}, {"code": "070103001", "name": "水塔基础", "features": ["1.基础类型、埋深", "2.混凝土种类", "3.混凝土强度等级"], "unit": "m³"}, {"code": "070103002", "name": "水塔塔身", "features": ["1.塔身类型", "2.塔身高度", "3.混凝土种类", "4.混凝土强度等级"], "unit": "m³"}, {"code": "070103003", "name": "水塔水箱", "features": ["1.水箱容积", "2.混凝土种类", "3.混凝土强度等级"], "unit": "m³"}, {"code": "070103004", "name": "水塔环梁", "features": ["1.混凝土种类", "2.混凝土强度等级"], "unit": "m³"}, {"code": "070104001", "name": "基础", "features": ["1.基础类型、埋深", "2.混凝土种类", "3.混凝土强度等级"], "unit": "m³"}, {"code": "070104002", "name": "冷却塔柱", "features": ["1.混凝土种类", "2.混凝土强度等级"], "unit": "m³"}, {"code": "070104003", "name": "冷却塔\n内隔板", "features": ["1.隔板类型", "2.混凝土种类", "3.混凝土强度等级"], "unit": "m³"}, {"code": "070104004", "name": "冷却塔梁", "features": ["1.混凝土种类", "2.混凝土强度等级"], "unit": "m³"}, {"code": "070104004", "name": "冷却塔梁", "features": ["1.混凝土种类", "2.混凝土强度等级"], "unit": "m³"}, {"code": "070104005", "name": "冷却塔顶板", "features": ["1.混凝土种类", "2.混凝土强度等级", "3.板类型"], "unit": "m³"}, {"code": "070104006", "name": "外部围护结 构(混凝土)", "features": ["1.墙板类型", "2.混凝土种类", "3.混凝土强度等级"], "unit": "m³"}, {"code": "070105001", "name": "基础", "features": [], "unit": "m³"}, {"code": "070105002", "name": "水池底板", "features": [], "unit": "m³"}, {"code": "070105003", "name": "水池壁板", "features": [], "unit": "m³"}, {"code": "070105004", "name": "人字柱", "features": ["1.混凝土种类", "2.混凝土强度等级"], "unit": "m³"}, {"code": "070105005", "name": "塔壁", "features": ["1.混凝土种类", "2.混凝土强度等级 3.壁厚"], "unit": "m³"}, {"code": "070105006", "name": "淋水构架", "features": ["1.淋水面积", "2.混凝土种类", "3.混凝土强度等级"], "unit": "m³"}, {"code": "070105007", "name": "水槽", "features": ["1.混凝土种类", "2.混凝土强度等级"], "unit": "m³"}, {"code": "070105008", "name": "中央竖井", "features": ["1.竖井顶标高", "2.竖井壁厚", "3.竖井内径", "4.混凝土种类", "5.混凝土强度等级"], "unit": "m³"}, {"code": "070106001", "name": "烟囱基础", "features": ["1.烟囱高度", "2.烟囱上口内径", "3.基础类型", "4.混凝土种类", "5.混凝土强度等级"], "unit": "m³"}, {"code": "070106002", "name": "烟囱筒壁", "features": ["1.烟囱高度", "2.烟囱上口内径", "3.混凝土种类", "4.混凝土强度等级"], "unit": "m³"}, {"code": "070106003", "name": "烟囱隔热层", "features": ["1.烟囱高度", "2.烟囱上口内径", "3.隔热层材料品种、 规格"], "unit": "m³"}, {"code": "070106004", "name": "烟囱内衬", "features": ["1.烟囱高度", "2.烟囱上口内径", "3. 内衬材料品种、 规格"], "unit": "m³"}, {"code": "070107001", "name": "烟道顶板", "features": ["1.混凝土种类", "2.混凝土强度等级"], "unit": "m³"}, {"code": "070107002", "name": "烟道壁板", "features": ["1.混凝土种类", "2.混凝土强度等级"], "unit": "m³"}, {"code": "070107003", "name": "烟道底板", "features": ["1.混凝土种类", "2.混凝土强度等级"], "unit": "m³"}, {"code": "070107004", "name": "烟道隔热层", "features": ["1.烟道断面净空尺 寸、长度", "2.隔热层材料品 种、规格"], "unit": "m³"}, {"code": "070107005", "name": "烟道内衬", "features": ["1.烟道断面净空尺 寸、长度", "2. 内衬材料品种、 规格"], "unit": "m³"}, {"code": "070108001", "name": "隧道底板", "features": ["1 . 隧道断面净空 尺寸", "2.混凝土种类", "3.混凝土强度等级"], "unit": "m³"}, {"code": "070108002", "name": "隧道壁板", "features": ["1 . 隧道断面净空 尺寸", "2.混凝土种类", "3.混凝土强度等级"], "unit": "m³"}, {"code": "070108003", "name": "隧道顶板", "features": ["1 . 隧道断面净空 尺寸", "2.混凝土种类", "3.混凝土强度等级"], "unit": "m³"}, {"code": "070109001", "name": "沟道(槽) 底板", "features": ["1.沟道断面净空尺寸", "2.混凝土种类", "3.混凝土强度等级"], "unit": "m³"}, {"code": "070109002", "name": "沟道(槽) 壁板", "features": ["1.沟道断面净空尺寸", "2.混凝土种类", "3.混凝土强度等级"], "unit": "m³"}, {"code": "070109003", "name": "沟道(槽) 盖板", "features": ["1.单块盖板尺寸", "2.混凝土种类", "3.混凝土强度等级", "4.砂浆或细石混凝 土强度等级"], "unit": "m³"}, {"code": "070109004", "name": "充砂", "features": ["砂种类"], "unit": "m³"}, {"code": "070110001", "name": "基础", "features": ["1.基础类型、埋深", "2.混凝土种类", "3.混凝土强度等级"], "unit": "m³"}, {"code": "070110002", "name": "刮料层", "features": ["1.刮料层组成：矩形", "柱、梁板、挑檐板、 筒壁", "2.混凝土种类", "3混凝土强度等级"], "unit": "m³"}, {"code": "070110003", "name": "喷淋层", "features": ["1.喷淋层组成：劲性 梁、矩形墙", "2.混凝土种类", "3.混凝土强度等级"], "unit": "m³"}, {"code": "070110004", "name": "其他部位", "features": ["1.其他部位组成：塔  顶板、塔顶挑檐板、 环形梁、电梯井壁、 楼梯间平台板", "2.混凝土种类", "3.混凝土强度等级"], "unit": "m³"}, {"code": "070110005", "name": "楼梯预制 构件", "features": ["1.楼梯预制构件类  型：踏步板、平台板", "2.混凝土强度等级"], "unit": "m³"}, {"code": "070111001", "name": "支架基础", "features": ["1.基础类型、埋深", "2.混凝土种类", "3.混凝土强度等级"], "unit": "m³"}, {"code": "070111002", "name": "混凝土支架", "features": ["1.支架类型", "2.混凝土种类", "3.混凝土强度等级"], "unit": "m³"}, {"code": "070111003", "name": "预制梁", "features": ["1.单件体积", "2.混凝土种类", "3.混凝土强度等级", "4.砂浆强度等级、配 合比"], "unit": "1.m³\n2.根"}, {"code": "070111004", "name": "预制走道板", "features": ["1.构件尺寸", "2.混凝土种类", "3.混凝土强度等级", "4.砂浆强度等级、配 合比"], "unit": "1.m³\n2.块"}, {"code": "070121005", "name": "压型钢板 围护结构", "features": ["1.钢材品种、规格 2.压型钢板厚度、复", "合板厚度", "3.复合板夹心材料品 种、层数、型号、规格"], "unit": "m²"}, {"code": "070111006", "name": "其他围护\n结构", "features": ["1.围护材料品种、规", "2.安装方式"], "unit": "m²"}, {"code": "070112001", "name": "井", "features": ["1.井类型、规格尺寸", "2.垫层材料种类、 厚度", "3.混凝土种类", "4.混凝土强度等级", "5.砂浆强度等级、配 合比", "6.防潮层材料种类"], "unit": "座"}, {"code": "070113001", "name": "电梯井基础", "features": ["1.基础类型", "2.混凝土种类", "3.混凝土强度等级"], "unit": "m³"}, {"code": "070113002", "name": "电梯井壁", "features": ["1.井壁高度", "2.井壁厚度", "3.混凝土种类", "4.混凝土强度等级"], "unit": "m³"}, {"code": "070201001", "name": "烟囱基础", "features": ["1.烟囱高度", "2.烟囱上口内径", "3.基础类型", "4.砌块品种、规格、 强度等级", "5.砂浆强度等级"], "unit": "m³"}, {"code": "070201002", "name": "烟囱筒壁", "features": ["1.烟囱高度", "2.烟囱上口内径", "3.砌块品种、规格、 强度等级", "4.勾缝要求", "5.砂浆强度等级、 配合比"], "unit": "m³"}, {"code": "070201003", "name": "烟道口 加固框", "features": ["1.烟囱高度", "2.烟囱上口内径", "3.混凝土种类", "4.混凝土强度等级"], "unit": "m³"}, {"code": "070201004", "name": "烟囱顶部\n圈梁", "features": ["1.烟囱高度", "2.烟囱上口内径", "3.混凝土种类", "4.混凝土强度等级"], "unit": "m³"}, {"code": "070202001", "name": "烟道", "features": ["1.烟道断面净空尺 寸、长度", "2.砌块品种、规格、 强度等级", "3.勾缝要求", "4.砂浆强度等级、配 合比"], "unit": "m³"}, {"code": "070202002", "name": "烟道\n预制顶板", "features": ["1.烟道顶板厚度", "2.混凝土种类", "3.混凝土强度等级"], "unit": "m³"}, {"code": "070203001", "name": "沟道(槽)", "features": ["1.沟道断面净空尺寸", "2.砌块品种、规格、 强度等级", "3.砂浆类别与强度 等级"], "unit": "m³"}, {"code": "070204001", "name": "井", "features": ["1.井类型、规格尺寸", "2.砌块种类、规格", "3.勾缝要求", "4.垫层材料种类、 厚度", "5.砂浆强度等级、配 合比", "6.防潮层材料种类"], "unit": "座"}, {"code": "070205001", "name": "铸铁盖板", "features": ["盖板规格型号"], "unit": "块"}, {"code": "070205002", "name": "玻璃钢盖板", "features": ["盖板规格型号"], "unit": "块"}, {"code": "070301001", "name": "特殊构筑物\n(烟囱、水塔、\n电梯井等)\n脚手架", "features": ["1.搭设方式", "2.构筑物几何尺寸、 高度"], "unit": "座"}, {"code": "070302001", "name": "池类", "features": ["1.构筑物形状", "2.几何尺寸", "3.壁、梁、柱、隔墙 厚度"], "unit": "m²"}, {"code": "070302002", "name": "贮仓类", "features": ["1.构筑物形状", "2.几何尺寸", "3.壁、梁、柱、隔墙 厚度"], "unit": "m²"}, {"code": "070302003", "name": "水塔", "features": ["1.构筑物形状", "2.几何尺寸", "3.壁、梁、柱、隔墙 厚度"], "unit": "m²"}, {"code": "070302004", "name": "机械通风 冷却塔", "features": ["1.构筑物形状", "2.几何尺寸", "3.壁、梁、柱、隔墙 厚度"], "unit": "m²"}, {"code": "070302005", "name": "双曲线\n自然通风\n冷却塔", "features": ["1.构筑物形状", "2.几何尺寸", "3.壁、梁、柱、隔墙 厚度"], "unit": "m²"}, {"code": "070302006", "name": "烟囱", "features": ["1.构筑物形状", "2.几何尺寸", "3.壁、梁、柱、隔墙厚度"], "unit": "m²"}, {"code": "070302007", "name": "烟道", "features": ["1.构筑物形状", "2.几何尺寸", "3.壁、梁、柱、隔墙厚度"], "unit": "m²"}, {"code": "070302008", "name": "工业隧道", "features": ["1.构筑物形状", "2.几何尺寸", "3.壁、梁、柱、隔墙厚度"], "unit": "m²"}, {"code": "070302009", "name": "沟道", "features": ["1.构筑物形状", "2.几何尺寸", "3.壁、梁、柱、隔墙厚度"], "unit": "m²"}, {"code": "070302010", "name": "造粒塔", "features": ["1.构筑物形状", "2.几何尺寸", "3.壁、梁、柱、隔墙厚度"], "unit": "m²"}, {"code": "070302011", "name": "输送栈桥", "features": ["1.构筑物形状", "2.几何尺寸", "3.壁、梁、柱、隔墙厚度"], "unit": "m²"}, {"code": "070302012", "name": "井类", "features": ["1.构筑物形状", "2.几何尺寸", "3.壁、梁、柱、隔墙厚度"], "unit": "m²"}, {"code": "070302013", "name": "电梯井", "features": ["1.构筑物形状", "2.几何尺寸", "3.壁、梁、柱、隔墙厚度"], "unit": "m²"}, {"code": "070302014", "name": "滑升模板", "features": ["1.构筑物形状", "2.几何尺寸", "3.壁、梁、柱、隔墙厚度"], "unit": "m³"}, {"code": "070303001", "name": "垂直运输", "features": ["1.构筑物类型", "2.结构形式"], "unit": "1.m³\n2.座"}, {"code": "070304001", "name": "大型机械 设备进出 场及安拆", "features": ["1.机械设备名称", "2.机械设备规格型号"], "unit": "台次"}, {"code": "070305001", "name": "成井", "features": ["1.成井方式", "2.地层情况", "3.成井直径", "4.井(滤)管类型、直径"], "unit": "m"}, {"code": "070305001", "name": "成井", "features": ["1.成井方式", "2.地层情况", "3.成井直径", "4.井(滤)管类型、直径"], "unit": "m"}, {"code": "070305002", "name": "排水、降水", "features": ["1.机械规格型号", "2.降排水管规格"], "unit": "昼夜"}, {"code": "070306001", "name": "安全文明施工", "features": [], "unit": ""}, {"code": "070306001", "name": "安全文明施工", "features": [], "unit": ""}, {"code": "070306002", "name": "夜间施工", "features": [], "unit": ""}, {"code": "070306003", "name": "二次搬运", "features": [], "unit": ""}, {"code": "070306004", "name": "冬雨季施工", "features": [], "unit": ""}, {"code": "070306005", "name": "地上、地下设施、建筑物 的临时保护设施", "features": [], "unit": ""}, {"code": "070306006", "name": "已完工程及设备保护", "features": [], "unit": ""}, {"code": "070306007", "name": "非夜间施工照明", "features": [], "unit": ""}, {"code": "070306008", "name": "构筑物特殊支护措施", "features": [], "unit": ""}]